sdfascii.py
sdfascii-0.8.2.dist-info/AUTHORS.md
sdfascii-0.8.2.dist-info/LICENSE.txt
sdfascii-0.8.2.dist-info/METADATA
sdfascii-0.8.2.dist-info/WHEEL
sdfascii-0.8.2.dist-info/top_level.txt
sdfascii-0.8.2.dist-info/RECORD
