Metadata-Version: 2.1
Name: sdfascii
Version: 0.8.2
Summary: Read HP SDF binary and ASCII files
Home-page: http://github.com/questrail/sdfascii
Author: Matthew Rankin
Author-email: matthew@questrail.com
License: MIT
Classifier: Programming Language :: Python
Classifier: Programming Language :: Python :: 3
Classifier: Programming Language :: Python :: 3.8
Classifier: Programming Language :: Python :: 3.9
Classifier: Programming Language :: Python :: 3.10
Classifier: Programming Language :: Python :: 3.11
Classifier: License :: OSI Approved :: MIT License
Classifier: Development Status :: 3 - Alpha
Classifier: Operating System :: OS Independent
Classifier: Intended Audience :: Developers
Classifier: Topic :: Software Development :: Libraries :: Python Modules
Requires: numpy (>=1.22.0)
License-File: LICENSE.txt
License-File: AUTHORS.md
